snippyts/__init__.py
snippyts/metrics.py
snippyts/preprocessing.py
snippyts/trie.py
snippyts/utilities.py
snippyts/vocabulary_tools.py
snippyts-0.3.0.dist-info/METADATA
snippyts-0.3.0.dist-info/WHEEL
snippyts-0.3.0.dist-info/top_level.txt
snippyts-0.3.0.dist-info/RECORD
