Metadata-Version: 2.4
Name: snippyts
Version: 0.3.0
Summary: Miscellaneous utility scripts and Python objects for agile development.
Author-email: Jordi Carrera Ventura <jordi.carrera.ventura@gmail.com>
Project-URL: GitHub repository, https://github.com/JordiCarreraVentura/snippyts
Project-URL: pypi page, https://pypi.org/project/snippyts
Classifier: Programming Language :: Python :: 3
Classifier: Operating System :: OS Independent
Requires-Python: >=3.9
Requires-Dist: build>=1.2.2.post1
Requires-Dist: flashtext2>=1.1.0
Requires-Dist: fuzzyset2>=0.2.4
Requires-Dist: nltk==3.9.1
Requires-Dist: pytest>=8.3.3
Requires-Dist: PyYAML==6.0.2
Requires-Dist: scikit-learn==1.6.1
Requires-Dist: tqdm==4.67.1
Requires-Dist: twine>=5.1.1
Requires-Dist: Unidecode>=1.3.8
